becke/becke.cpython-37m-darwin.so
becke-0.0.15.dist-info/LICENSE
becke-0.0.15.dist-info/METADATA
becke-0.0.15.dist-info/WHEEL
becke-0.0.15.dist-info/top_level.txt
becke-0.0.15.dist-info/RECORD
