Metadata-Version: 2.1
Name: becke
Version: 0.0.15
Summary: Fast and memory efficient implementation of becke weights.
Home-page: https://github.com/tczorro/becke.git
Author: UNKNOWN
Author-email: yxt1991@gmail.com
License: UNKNOWN
Platform: UNKNOWN
Classifier: License :: OSI Approved :: BSD License
Classifier: Operating System :: OS Independent
Requires-Dist: numpy (>=1.16)
Requires-Dist: cython (>=0.29)
